weblablib/__init__.py
weblablib/config.py
weblablib/exc.py
weblablib/ops.py
weblablib/tasks.py
weblablib/users.py
weblablib/utils.py
weblablib/views.py
weblablib/backends/__init__.py
weblablib/backends/redis_manager.py
weblablib-0.5.7.dist-info/METADATA
weblablib-0.5.7.dist-info/RECORD
weblablib-0.5.7.dist-info/WHEEL
weblablib-0.5.7.dist-info/top_level.txt
