Metadata-Version: 2.1
Name: weblablib
Version: 0.5.7
Summary: WebLab-Deusto library for creating unmanaged laboratories
Home-page: https://developers.labsland.com/weblablib/
Author: LabsLand
Author-email: dev@labsland.com
License: GNU AGPL v3
Project-URL: Documentation, https://developers.labsland.com/weblablib/en/stable/
Project-URL: Code, https://github.com/weblabdeusto/weblablib
Project-URL: Issue tracker, https://github.com/weblabdeusto/weblablib/issues
Platform: UNKNOWN
Classifier: Development Status :: 4 - Beta
Classifier: Environment :: Web Environment
Classifier: Intended Audience :: Developers
Classifier: License :: OSI Approved :: GNU Affero General Public License v3
Classifier: Operating System :: OS Independent
Classifier: Programming Language :: Python
Classifier: Programming Language :: Python :: 2
Classifier: Programming Language :: Python :: 2.7
Classifier: Programming Language :: Python :: 3
Classifier: Programming Language :: Python :: 3.6
Classifier: Programming Language :: Python :: 3.7
Classifier: Topic :: Education
Classifier: Topic :: Internet :: WWW/HTTP
Classifier: Topic :: Software Development :: Libraries :: Application Frameworks
